tritonix/configs
tritonix/fused/glu.py
tritonix/matrix/__init__.py
tritonix/matrix/mma.py
tritonix/matrix/reshape.py
tritonix/matrix/sparse.py
tritonix/utils/__init__.py
tritonix/utils/initialize.py
tritonix/utils/torch.py
tritonix/utils/trie.py
tritonix/utils/triton.py
tritonix/utils/utils.py
tritonix-0.1.0.dist-info/LICENSE
tritonix-0.1.0.dist-info/METADATA
tritonix-0.1.0.dist-info/WHEEL
tritonix-0.1.0.dist-info/RECORD
