Metadata-Version: 2.3
Name: tritonix
Version: 0.1.0
Summary: 
License: CC-BY-NC
Keywords: triton,kernel,ai,deep-learning
Author: Ayoub G.
Author-email: dev@ayghri.com
Requires-Python: >=3.9,<3.14
Classifier: License :: Other/Proprietary License
Classifier: Programming Language :: Python :: 3
Classifier: Programming Language :: Python :: 3.9
Classifier: Programming Language :: Python :: 3.10
Classifier: Programming Language :: Python :: 3.11
Classifier: Programming Language :: Python :: 3.12
Classifier: Programming Language :: Python :: 3.13
Requires-Dist: matplotlib (>=3.10.5,<4.0.0)
Requires-Dist: numpy (>=2.3.2,<3.0.0)
Requires-Dist: pandas (>=2.3.1,<3.0.0)
Requires-Dist: pytest (>=8.4.1,<9.0.0)
Requires-Dist: scikit-optimize (>=0.10.2,<0.11.0)
Requires-Dist: scipy (>=1.16.1,<2.0.0)
Requires-Dist: tabulate (>=0.9.0,<0.10.0)
Requires-Dist: torch (>=2.7.1,<3.0.0)
